plottingtools/__init__.py
plottingtools/bar_chart.py
plottingtools/plot.py
plottingtools/util.py
plottingtools-1.0.1.dist-info/LICENSE
plottingtools-1.0.1.dist-info/METADATA
plottingtools-1.0.1.dist-info/WHEEL
plottingtools-1.0.1.dist-info/top_level.txt
plottingtools-1.0.1.dist-info/RECORD
