Metadata-Version: 2.1
Name: plottingtools
Version: 1.0.1
Summary: A collection of tools for plotting graphs that I have used often enough (or are complex enough) for me to add to a repo
Home-page: https://github.com/JoshuaBeard/plottingtools
Author: Joshua Beard
Author-email: joshuabeard92@gmail.com
License: UNKNOWN
Platform: UNKNOWN
Requires-Dist: numpy
Requires-Dist: matplotlib
